beaconclient/__init__.py
beaconclient/asyncio.py
beaconclient/config.py
beaconclient/protocol.py
beaconclient/py.typed
beaconclient/syncio.py
beaconclient/utils.py
esrf_beacon_client-1.0.dist-info/METADATA
esrf_beacon_client-1.0.dist-info/WHEEL
esrf_beacon_client-1.0.dist-info/top_level.txt
esrf_beacon_client-1.0.dist-info/RECORD
